teleauth/__init__.py
teleauth/auth.py
teleauth/store.py
teleauth-1.1.1.dist-info/LICENSE
teleauth-1.1.1.dist-info/METADATA
teleauth-1.1.1.dist-info/WHEEL
teleauth-1.1.1.dist-info/top_level.txt
teleauth-1.1.1.dist-info/RECORD
